README.md
setup.cfg
setup.py
uib_vfeatures/__init__.py
uib_vfeatures/color.py
uib_vfeatures/contours.py
uib_vfeatures/masks.py
uib_vfeatures/texture.py
uib_vfeatures.egg-info/PKG-INFO
uib_vfeatures.egg-info/SOURCES.txt
uib_vfeatures.egg-info/dependency_links.txt
uib_vfeatures.egg-info/not-zip-safe
uib_vfeatures.egg-info/requires.txt
uib_vfeatures.egg-info/top_level.txt