Metadata-Version: 2.1
Name: uib-vfeatures
Version: 0.5.4
Summary: Vision features of generalistic use
Home-page: https://gitlab.com/miquelca32/features
Author: Miquel Miró Nicolau, Bernat Galmés Rubert, Dr. Gabriel Moyà Alcover
Author-email: miquelca32@gmail.com, bernat_galmes@hotmail.com, gabriel_moya@uib.es
License: MIT
Keywords: Features extraction,Machine Learning,Computer Vision
Platform: UNKNOWN
